<Archive code="0">
    <Rect name="WindowFrame" value="Rect(1163.000000,76.000000,1565.000000,113.000000)" />
    <Bool name="IsPrimary" value="false" />
    <Archive code="0" name="position_map">
        <Array name="item_id">
            <Identity value="Identity(57008,252490)" />
            <Identity value="Identity(57008,215577)" />
            <Identity value="Identity(57008,215568)" />
            <Identity value="Identity(57008,215599)" />
            <Identity value="Identity(57008,215578)" />
        </Array>
        <Array name="item_pos">
            <IPoint value="IPoint(0,0)" />
            <IPoint value="IPoint(1,0)" />
            <IPoint value="IPoint(2,0)" />
            <IPoint value="IPoint(3,0)" />
            <IPoint value="IPoint(4,0)" />
        </Array>
    </Archive>
    <Int32 name="selected_bar" value="0" />
    <Int32 name="bar_orientation" value="0" />
</Archive>
